beaker_kernel/__init__.py
beaker_kernel/kernel.json
beaker_kernel/kernel.py
beaker_kernel/builder/__init__.py
beaker_kernel/builder/beaker.py
beaker_kernel/builder/hooks.py
beaker_kernel/builder/templates.py
beaker_kernel/builder/utils.py
beaker_kernel/cli/__init__.py
beaker_kernel/cli/app.py
beaker_kernel/cli/config.py
beaker_kernel/cli/context.py
beaker_kernel/cli/helpers.py
beaker_kernel/cli/main.py
beaker_kernel/cli/project.py
beaker_kernel/cli/running.py
beaker_kernel/cli/subkernel.py
beaker_kernel/contexts/__init__.py
beaker_kernel/contexts/default/__init__.py
beaker_kernel/contexts/default/agent.py
beaker_kernel/contexts/default/context.py
beaker_kernel/contexts/default/default_payload.json
beaker_kernel/lib/__init__.py
beaker_kernel/lib/agent.py
beaker_kernel/lib/agent_tasks.py
beaker_kernel/lib/app.py
beaker_kernel/lib/autodiscovery.py
beaker_kernel/lib/config.py
beaker_kernel/lib/context.py
beaker_kernel/lib/jupyter_kernel_proxy.py
beaker_kernel/lib/message_types.py
beaker_kernel/lib/subkernel.py
beaker_kernel/lib/types.py
beaker_kernel/lib/utils.py
beaker_kernel/lib/workflow.py
beaker_kernel/lib/code_analysis/__init__.py
beaker_kernel/lib/code_analysis/analysis_agent.py
beaker_kernel/lib/code_analysis/analysis_types.py
beaker_kernel/lib/code_analysis/analyzer.py
beaker_kernel/lib/code_analysis/message_types.py
beaker_kernel/lib/code_analysis/rules/__init__.py
beaker_kernel/lib/code_analysis/rules/base.py
beaker_kernel/lib/code_analysis/rules/trust/__init__.py
beaker_kernel/lib/code_analysis/rules/trust/categories.py
beaker_kernel/lib/code_analysis/rules/trust/rules.py
beaker_kernel/lib/exporters/__init__.py
beaker_kernel/lib/exporters/full_context_notebook.py
beaker_kernel/lib/exporters/streamline.py
beaker_kernel/lib/integrations/__init__.py
beaker_kernel/lib/integrations/adhoc.py
beaker_kernel/lib/integrations/base.py
beaker_kernel/lib/templates/__init__.py
beaker_kernel/lib/templates/agent_file.py
beaker_kernel/lib/templates/context_file.py
beaker_kernel-1.14.0.dist-info/METADATA
beaker_kernel-1.14.0.dist-info/WHEEL
beaker_kernel-1.14.0.dist-info/entry_points.txt
beaker_kernel-1.14.0.dist-info/licenses/LICENSE.txt
beaker_kernel-1.14.0.dist-info/RECORD
