Metadata-Version: 2.4
Name: beaker-kernel
Version: 1.14.0
Project-URL: Documentation, https://github.com/jataware/beaker-kernel#readme
Project-URL: Issues, https://github.com/jataware/beaker-kernel/issues
Project-URL: Source, https://github.com/jataware/beaker-kernel
Author-email: Matthew Printz <matt@jataware.com>
License-Expression: MIT
License-File: LICENSE.txt
Classifier: Development Status :: 4 - Beta
Classifier: Programming Language :: Python
Classifier: Programming Language :: Python :: 3.10
Classifier: Programming Language :: Python :: 3.11
Classifier: Programming Language :: Python :: Implementation :: CPython
Classifier: Programming Language :: Python :: Implementation :: PyPy
Requires-Python: >=3.10
Requires-Dist: adhoc-api>=2.6.2
Requires-Dist: archytas>=1.6.5
Requires-Dist: click~=8.1
Requires-Dist: dill
Requires-Dist: hatch
Requires-Dist: jinja2~=3.1.2
Requires-Dist: jupyterlab-server<3,>=2.22.1
Requires-Dist: jupyterlab~=4.0
Requires-Dist: matplotlib
Requires-Dist: numpy
Requires-Dist: openpyxl
Requires-Dist: pandas
Requires-Dist: python-dotenv~=1.0
Requires-Dist: requests<3,>=2.24
Requires-Dist: scipy
Requires-Dist: six
Requires-Dist: toml
Requires-Dist: tornado>=6.4.0
Requires-Dist: tree-sitter-julia
Requires-Dist: tree-sitter-python
Requires-Dist: tree-sitter<0.25.0
Requires-Dist: watchdog~=3.0
Requires-Dist: xarray
